{
    "chain_name": "Lava",
    "api": ["https://lava.declab.pro:443","https://lava-api.polkachu.com:443"],
    "rpc": ["https://lava.declab.pro:26613","https://lava-rpc.polkachu.com:443"],
    "snapshot_provider": "https://lava.declab.pro/latest.tar.lz4",
    "sdk_version": "0.45.11",
    "coin_type": "118",
    "min_tx_fee": "800",
    "addr_prefix": "lava",
    "logo": "/logos/lava.png",
    "assets": [
      {
        "base": "ulava",
        "symbol": "LAVA",
        "exponent": "6",
        "coingecko_id": "lava-network", 
        "logo": "/logos/lava.png"
      }
    ]
  }
